pyaccount/__init__.py
pyaccount/pyaccount.py
pyaccount-0.0.4.dist-info/METADATA
pyaccount-0.0.4.dist-info/RECORD
pyaccount-0.0.4.dist-info/WHEEL
pyaccount-0.0.4.dist-info/entry_points.txt
pyaccount-0.0.4.dist-info/top_level.txt
