Metadata-Version: 2.1
Name: pyaccount
Version: 0.0.4
Summary: a tiny and smart cli to store account and passwd
Home-page: https://gitee.com/zxybird/pyaccount.git
Author: Bird.Zhang
Author-email: 476100281@qq.com
License: MIT
Platform: UNKNOWN
